{"name":"Airy-jariya","tagline":"","body":"# Hello  ...  ^_^\r\n\r\n![](https://fbcdn-sphotos-f-a.akamaihd.net/hphotos-ak-xap1/v/t1.0-9/10922602_782868461782611_505077419411232153_n.jpg?oh=4271df07adafaa5e0703a6db52d1c248&oe=555761CB&__gda__=1433335426_36ea7260fa03f67e95ccb50e40892693)\r\n\r\n## Jariya Kuyduang \r\n#### My nickname is Air\r\n#### sex :female\r\n#### I’me 20 years old.\r\n#### My birthday is the 13th of December 1994.\r\n#### I am studying Information Systemat at Prince of Songkla University.\r\n#### My favorite food is Noodle and Pad Ka Prao.\r\n#### My favorite color is blue green.\r\n#### My hobby is drawing pictures.\r\n#### Nice to meet you..\r\n\r\n## My Family\r\n![](https://scontent-b-hkg.xx.fbcdn.net/hphotos-xfp1/v/l/t1.0-9/10543621_697998776936247_8833398193796173261_n.jpg?oh=cb03be0baae5a986585e952b058ab6dd&oe=555D2F5A)\r\n\r\n## The Gang\r\n![](https://scontent-a-hkg.xx.fbcdn.net/hphotos-xfp1/v/t1.0-9/10426183_889314487745607_3082533109287234634_n.jpg?oh=7b19ca282cbfb450b3bf520b302fbbee&oe=55691784)\r\n\r\n## Party with The Gang\r\n![](https://scontent-b-hkg.xx.fbcdn.net/hphotos-xpa1/v/t1.0-9/10428679_882363205107402_6721220405326531215_n.jpg?oh=2cfd80e4b9e30f49810f08f6958a5399&oe=555B68A9)","google":"","note":"Don't delete this file! It's used internally to help with page regeneration."}